viu_chem/MSI_Process.py
viu_chem/__init__.py
viu_chem/analytes.py
viu_chem/chem412.py
viu_chem/jm_helpers.py
viu_chem/msi_pkg/SA.py
viu_chem/msi_pkg/__init__.py
viu_chem/msi_pkg/clustering.py
viu_chem/msi_pkg/io.py
viu_chem/msi_pkg/plot.py
viu_chem/msi_pkg/utils.py
viu_chem/msi_preprocessing_flow/README.md
viu_chem/msi_preprocessing_flow/Snakefile
viu_chem/msi_preprocessing_flow/__init__.py
viu_chem/msi_preprocessing_flow/dag.pdf
viu_chem/msi_preprocessing_flow/data/config.yaml
viu_chem/msi_preprocessing_flow/scripts/alignment/alignment.py
viu_chem/msi_preprocessing_flow/scripts/alignment/get_reference_spectrum.py
viu_chem/msi_preprocessing_flow/scripts/deisotoping/deisotope.py
viu_chem/msi_preprocessing_flow/scripts/deisotoping/get_deisotoped_mz.py
viu_chem/msi_preprocessing_flow/scripts/internorm/get_median_overall_spectrum.py
viu_chem/msi_preprocessing_flow/scripts/internorm/internorm.py
viu_chem/msi_preprocessing_flow/scripts/intranorm/intranorm.py
viu_chem/msi_preprocessing_flow/scripts/matrix_removal/get_matrix_pixels_from_mz_list.py
viu_chem/msi_preprocessing_flow/scripts/matrix_removal/get_matrix_pixels_from_segmentation.py
viu_chem/msi_preprocessing_flow/scripts/matrix_removal/get_sample_matrix_peaks.py
viu_chem/msi_preprocessing_flow/scripts/matrix_removal/matrix_removal.py
viu_chem/msi_preprocessing_flow/scripts/outlier_detection/umap_outlier_detection.py
viu_chem/msi_preprocessing_flow/scripts/peak_filtering/filter_spatial_coherence.py
viu_chem/msi_preprocessing_flow/scripts/peak_filtering/get_mzs_above_spatial_coherence_thr.py
viu_chem/msi_preprocessing_flow/scripts/peak_filtering/spatial_coherence.py
viu_chem/msi_preprocessing_flow/scripts/peak_picking/peak_picking.py
viu_chem/msi_segmentation_flow/README.md
viu_chem/msi_segmentation_flow/Snakefile
viu_chem/msi_segmentation_flow/__init__.py
viu_chem/msi_segmentation_flow/dag.pdf
viu_chem/msi_segmentation_flow/data/config.yaml
viu_chem/msi_segmentation_flow/scripts/multi_sample_segmentation.py
viu_chem-0.1.18.dist-info/LICENSE
viu_chem-0.1.18.dist-info/METADATA
viu_chem-0.1.18.dist-info/WHEEL
viu_chem-0.1.18.dist-info/RECORD
