Metadata-Version: 2.3
Name: viu-chem
Version: 0.1.18
Summary: Collection of commonly used functions by VIU chemistry
Author: Joseph Monaghan
Author-email: Joseph_Monaghan@outlook.com
Requires-Python: >=3.12
Classifier: Programming Language :: Python :: 3
Classifier: Programming Language :: Python :: 3.12
Classifier: Programming Language :: Python :: 3.13
Requires-Dist: imzml-writer (>=1.1.1,<2.0.0)
Requires-Dist: matplotlib (>=3.10.0,<4.0.0)
Requires-Dist: numpy (>=2.2.3,<3.0.0)
Requires-Dist: pandas (>=2.2.3,<3.0.0)
Requires-Dist: pyimzml (>=1.5.5,<2.0.0)
Requires-Dist: pymzml (>=2.5.11,<3.0.0)
Requires-Dist: scipy (>=1.15.3,<2.0.0)
